Airflow_DingDing/DingDingAlarmModule.py
Airflow_DingDing/__init__.py
Airflow_DingDing-0.1.1.dist-info/METADATA
Airflow_DingDing-0.1.1.dist-info/WHEEL
Airflow_DingDing-0.1.1.dist-info/top_level.txt
Airflow_DingDing-0.1.1.dist-info/RECORD
