Metadata-Version: 2.1
Name: Airflow-DingDing
Version: 0.1.1
Summary: UNKNOWN
Home-page: https://xxxxxxxxx
Author: WangBensen
Author-email: bensen.wang@ycgame.com
License: Apache License
Platform: UNKNOWN
Classifier: Environment :: Web Environment
Classifier: Intended Audience :: Developers
Classifier: Operating System :: OS Independent
Classifier: Topic :: Text Processing :: Indexing
Classifier: Topic :: Utilities
Classifier: Topic :: Internet
Classifier: Topic :: Software Development :: Libraries :: Python Modules
Classifier: Programming Language :: Python
Classifier: Programming Language :: Python :: 3.8
Requires-Dist: requests (<=2.28.1)
